flaskerizer/__init__.py
flaskerizer/__main__.py
flaskerizer/flaskerizer_src/HTTP_status_dict.py
flaskerizer/flaskerizer_src/__init__.py
flaskerizer/flaskerizer_src/command_line_arguments.py
flaskerizer/flaskerizer_src/status_code_to_word.py
flaskerizer/flaskerizer_src/structure_directory.py
flaskerizer/flaskerizer_src/target_folders.py
flaskerizer/flaskerizer_src/write_app.py
flaskerizer/flaskerizer_src/examples/__init__.py
flaskerizer/flaskerizer_src/examples/Alstar_example/__init__.py
flaskerizer/flaskerizer_src/tests/__init__.py
flaskerizer/flaskerizer_src/tests/test_status_code_to_word.py
flaskerizer/flaskerizer_src/tests/test_structure_directory.py
flaskerizer/flaskerizer_src/tests/test_write_app.py
flaskerizer/flaskerizer_src/tests/testing_files/__init__.py
flaskerizer/flaskerizer_src/tests/testing_files/app_test_file.py
flaskerizer/flaskerizer_src/tests/testing_files/routes_test_file.py
flaskerizer/flaskerizer_src/tests/testing_files/large_Test_application_test_folder/__init__.py
flaskerizer/flaskerizer_src/tests/testing_files/large_Test_application_test_folder/setup.py
flaskerizer/flaskerizer_src/tests/testing_files/large_Test_application_test_folder/Test_application/__init__.py
flaskerizer/flaskerizer_src/tests/testing_files/large_Test_application_test_folder/Test_application/routes.py
flaskerizer-0.0.2.dist-info/METADATA
flaskerizer-0.0.2.dist-info/RECORD
flaskerizer-0.0.2.dist-info/WHEEL
flaskerizer-0.0.2.dist-info/entry_points.txt
flaskerizer-0.0.2.dist-info/top_level.txt
