Metadata-Version: 2.1
Name: flaskerizer
Version: 0.0.2
Summary: The Flaskerizer makes Bootstrap templates work "out of the box" with Flask.
Home-page: https://github.com/brettvanderwerff/Flaskerizer
Author: Brett Vanderwerff
Author-email: brett.vanderwerff@gmail.com
License: UNKNOWN
Platform: UNKNOWN
Classifier: Programming Language :: Python :: 2.7
Classifier: Programming Language :: Python :: 3.3
Classifier: Programming Language :: Python :: 3.4
Classifier: Programming Language :: Python :: 3.5
Classifier: Programming Language :: Python :: 3.6
Classifier: Programming Language :: Python :: 3.7
Classifier: Operating System :: OS Independent
Classifier: License :: OSI Approved :: GNU General Public License v2 (GPLv2)
Classifier: Framework :: Flask
Classifier: Operating System :: OS Independent
Classifier: Development Status :: 3 - Alpha
Requires-Dist: flask
